tesslate_chainlit/__init__.py
tesslate_chainlit/__main__.py
tesslate_chainlit/_utils.py
tesslate_chainlit/action.py
tesslate_chainlit/auth/__init__.py
tesslate_chainlit/auth/cookie.py
tesslate_chainlit/auth/jwt.py
tesslate_chainlit/cache.py
tesslate_chainlit/callbacks.py
tesslate_chainlit/chat_context.py
tesslate_chainlit/chat_settings.py
tesslate_chainlit/cli/__init__.py
tesslate_chainlit/config.py
tesslate_chainlit/context.py
tesslate_chainlit/copilot/dist/assets/logo_dark-IkGJ_IwC.svg
tesslate_chainlit/copilot/dist/assets/logo_light-Bb_IPh6r.svg
tesslate_chainlit/copilot/dist/index.js
tesslate_chainlit/data/__init__.py
tesslate_chainlit/data/acl.py
tesslate_chainlit/data/base.py
tesslate_chainlit/data/chainlit_data_layer.py
tesslate_chainlit/data/dynamodb.py
tesslate_chainlit/data/literalai.py
tesslate_chainlit/data/sql_alchemy.py
tesslate_chainlit/data/storage_clients/__init__.py
tesslate_chainlit/data/storage_clients/azure.py
tesslate_chainlit/data/storage_clients/azure_blob.py
tesslate_chainlit/data/storage_clients/base.py
tesslate_chainlit/data/storage_clients/gcs.py
tesslate_chainlit/data/storage_clients/s3.py
tesslate_chainlit/data/utils.py
tesslate_chainlit/discord/__init__.py
tesslate_chainlit/discord/app.py
tesslate_chainlit/element.py
tesslate_chainlit/emitter.py
tesslate_chainlit/frontend/dist/.DS_Store
tesslate_chainlit/frontend/dist/assets/DailyMotion-D4pwiJV4.js
tesslate_chainlit/frontend/dist/assets/DailyMotion-D4pwiJV4.js.map
tesslate_chainlit/frontend/dist/assets/DailyMotion-Dhcv5sag.js
tesslate_chainlit/frontend/dist/assets/DailyMotion-Dhcv5sag.js.map
tesslate_chainlit/frontend/dist/assets/Dataframe-C09mYchA.js
tesslate_chainlit/frontend/dist/assets/Dataframe-C09mYchA.js.map
tesslate_chainlit/frontend/dist/assets/Dataframe-qfyaMR2I.js
tesslate_chainlit/frontend/dist/assets/Dataframe-qfyaMR2I.js.map
tesslate_chainlit/frontend/dist/assets/Facebook-WDd_lPTH.js
tesslate_chainlit/frontend/dist/assets/Facebook-WDd_lPTH.js.map
tesslate_chainlit-2.5.5.dist-info/METADATA
tesslate_chainlit-2.5.5.dist-info/WHEEL
tesslate_chainlit-2.5.5.dist-info/entry_points.txt
tesslate_chainlit-2.5.5.dist-info/RECORD
